{"id":"node_modules/react/lib/ReactRef.js","dependencies":[{"name":"/Users/Mikey/Programming/open-source/react-scaffold/node_modules/react/package.json","includedInParent":true,"mtime":1534193414451},{"name":"/Users/Mikey/Programming/open-source/react-scaffold/package.json","includedInParent":true,"mtime":1534197385728},{"name":"/Users/Mikey/Programming/open-source/react-scaffold/.babelrc","includedInParent":true,"mtime":1534195938169},{"name":"./ReactOwner","loc":{"line":14,"column":25},"parent":"/Users/Mikey/Programming/open-source/react-scaffold/node_modules/react/lib/ReactRef.js","resolved":"/Users/Mikey/Programming/open-source/react-scaffold/node_modules/react/lib/ReactOwner.js"}],"generated":{"js":"/**\n * Copyright 2013-present, Facebook, Inc.\n * All rights reserved.\n *\n * This source code is licensed under the BSD-style license found in the\n * LICENSE file in the root directory of this source tree. An additional grant\n * of patent rights can be found in the PATENTS file in the same directory.\n *\n * @providesModule ReactRef\n */\n\n'use strict';\n\nvar ReactOwner = require('./ReactOwner');\n\nvar ReactRef = {};\n\nfunction attachRef(ref, component, owner) {\n  if (typeof ref === 'function') {\n    ref(component.getPublicInstance());\n  } else {\n    // Legacy ref\n    ReactOwner.addComponentAsRefTo(component, ref, owner);\n  }\n}\n\nfunction detachRef(ref, component, owner) {\n  if (typeof ref === 'function') {\n    ref(null);\n  } else {\n    // Legacy ref\n    ReactOwner.removeComponentAsRefFrom(component, ref, owner);\n  }\n}\n\nReactRef.attachRefs = function (instance, element) {\n  if (element === null || element === false) {\n    return;\n  }\n  var ref = element.ref;\n  if (ref != null) {\n    attachRef(ref, instance, element._owner);\n  }\n};\n\nReactRef.shouldUpdateRefs = function (prevElement, nextElement) {\n  // If either the owner or a `ref` has changed, make sure the newest owner\n  // has stored a reference to `this`, and the previous owner (if different)\n  // has forgotten the reference to `this`. We use the element instead\n  // of the public this.props because the post processing cannot determine\n  // a ref. The ref conceptually lives on the element.\n\n  // TODO: Should this even be possible? The owner cannot change because\n  // it's forbidden by shouldUpdateReactComponent. The ref can change\n  // if you swap the keys of but not the refs. Reconsider where this check\n  // is made. It probably belongs where the key checking and\n  // instantiateReactComponent is done.\n\n  var prevEmpty = prevElement === null || prevElement === false;\n  var nextEmpty = nextElement === null || nextElement === false;\n\n  return (\n    // This has a few false positives w/r/t empty components.\n    prevEmpty || nextEmpty || nextElement.ref !== prevElement.ref ||\n    // If owner changes but we have an unchanged function ref, don't update refs\n    typeof nextElement.ref === 'string' && nextElement._owner !== prevElement._owner\n  );\n};\n\nReactRef.detachRefs = function (instance, element) {\n  if (element === null || element === false) {\n    return;\n  }\n  var ref = element.ref;\n  if (ref != null) {\n    detachRef(ref, instance, element._owner);\n  }\n};\n\nmodule.exports = ReactRef;","map":{"mappings":[{"generated":{"line":1,"column":0},"source":"node_modules/react/lib/ReactRef.js","original":{"line":1,"column":0}},{"generated":{"line":12,"column":0},"source":"node_modules/react/lib/ReactRef.js","original":{"line":12,"column":0}},{"generated":{"line":14,"column":0},"source":"node_modules/react/lib/ReactRef.js","original":{"line":14,"column":0}},{"name":"ReactOwner","generated":{"line":14,"column":4},"source":"node_modules/react/lib/ReactRef.js","original":{"line":14,"column":4}},{"name":"require","generated":{"line":14,"column":17},"source":"node_modules/react/lib/ReactRef.js","original":{"line":14,"column":17}},{"generated":{"line":14,"column":25},"source":"node_modules/react/lib/ReactRef.js","original":{"line":14,"column":25}},{"generated":{"line":14,"column":39},"source":"node_modules/react/lib/ReactRef.js","original":{"line":14,"column":17}},{"generated":{"line":14,"column":40},"source":"node_modules/react/lib/ReactRef.js","original":{"line":14,"column":0}},{"generated":{"line":16,"column":0},"source":"node_modules/react/lib/ReactRef.js","original":{"line":16,"column":0}},{"name":"ReactRef","generated":{"line":16,"column":4},"source":"node_modules/react/lib/ReactRef.js","original":{"line":16,"column":4}},{"generated":{"line":16,"column":15},"source":"node_modules/react/lib/ReactRef.js","original":{"line":16,"column":15}},{"generated":{"line":16,"column":17},"source":"node_modules/react/lib/ReactRef.js","original":{"line":16,"column":0}},{"generated":{"line":18,"column":0},"source":"node_modules/react/lib/ReactRef.js","original":{"line":18,"column":0}},{"name":"attachRef","generated":{"line":18,"column":9},"source":"node_modules/react/lib/ReactRef.js","original":{"line":18,"column":9}},{"generated":{"line":18,"column":18},"source":"node_modules/react/lib/ReactRef.js","original":{"line":18,"column":0}},{"name":"ref","generated":{"line":18,"column":19},"source":"node_modules/react/lib/ReactRef.js","original":{"line":18,"column":19}},{"generated":{"line":18,"column":22},"source":"node_modules/react/lib/ReactRef.js","original":{"line":18,"column":0}},{"name":"component","generated":{"line":18,"column":24},"source":"node_modules/react/lib/ReactRef.js","original":{"line":18,"column":24}},{"generated":{"line":18,"column":33},"source":"node_modules/react/lib/ReactRef.js","original":{"line":18,"column":0}},{"name":"owner","generated":{"line":18,"column":35},"source":"node_modules/react/lib/ReactRef.js","original":{"line":18,"column":35}},{"generated":{"line":18,"column":40},"source":"node_modules/react/lib/ReactRef.js","original":{"line":18,"column":0}},{"generated":{"line":18,"column":42},"source":"node_modules/react/lib/ReactRef.js","original":{"line":18,"column":42}},{"generated":{"line":19,"column":0},"source":"node_modules/react/lib/ReactRef.js","original":{"line":19,"column":2}},{"generated":{"line":19,"column":6},"source":"node_modules/react/lib/ReactRef.js","original":{"line":19,"column":6}},{"name":"ref","generated":{"line":19,"column":13},"source":"node_modules/react/lib/ReactRef.js","original":{"line":19,"column":13}},{"generated":{"line":19,"column":16},"source":"node_modules/react/lib/ReactRef.js","original":{"line":19,"column":6}},{"generated":{"line":19,"column":21},"source":"node_modules/react/lib/ReactRef.js","original":{"line":19,"column":21}},{"generated":{"line":19,"column":31},"source":"node_modules/react/lib/ReactRef.js","original":{"line":19,"column":2}},{"generated":{"line":19,"column":33},"source":"node_modules/react/lib/ReactRef.js","original":{"line":19,"column":33}},{"name":"ref","generated":{"line":20,"column":0},"source":"node_modules/react/lib/ReactRef.js","original":{"line":20,"column":4}},{"name":"component","generated":{"line":20,"column":8},"source":"node_modules/react/lib/ReactRef.js","original":{"line":20,"column":8}},{"name":"getPublicInstance","generated":{"line":20,"column":18},"source":"node_modules/react/lib/ReactRef.js","original":{"line":20,"column":18}},{"generated":{"line":20,"column":35},"source":"node_modules/react/lib/ReactRef.js","original":{"line":20,"column":8}},{"generated":{"line":20,"column":37},"source":"node_modules/react/lib/ReactRef.js","original":{"line":20,"column":4}},{"generated":{"line":21,"column":0},"source":"node_modules/react/lib/ReactRef.js","original":{"line":21,"column":3}},{"generated":{"line":21,"column":3},"source":"node_modules/react/lib/ReactRef.js","original":{"line":19,"column":2}},{"generated":{"line":21,"column":9},"source":"node_modules/react/lib/ReactRef.js","original":{"line":21,"column":9}},{"generated":{"line":22,"column":0},"source":"node_modules/react/lib/ReactRef.js","original":{"line":22,"column":4}},{"name":"ReactOwner","generated":{"line":23,"column":0},"source":"node_modules/react/lib/ReactRef.js","original":{"line":23,"column":4}},{"name":"addComponentAsRefTo","generated":{"line":23,"column":15},"source":"node_modules/react/lib/ReactRef.js","original":{"line":23,"column":15}},{"generated":{"line":23,"column":34},"source":"node_modules/react/lib/ReactRef.js","original":{"line":23,"column":4}},{"name":"component","generated":{"line":23,"column":35},"source":"node_modules/react/lib/ReactRef.js","original":{"line":23,"column":35}},{"generated":{"line":23,"column":44},"source":"node_modules/react/lib/ReactRef.js","original":{"line":23,"column":4}},{"name":"ref","generated":{"line":23,"column":46},"source":"node_modules/react/lib/ReactRef.js","original":{"line":23,"column":46}},{"generated":{"line":23,"column":49},"source":"node_modules/react/lib/ReactRef.js","original":{"line":23,"column":4}},{"name":"owner","generated":{"line":23,"column":51},"source":"node_modules/react/lib/ReactRef.js","original":{"line":23,"column":51}},{"generated":{"line":23,"column":56},"source":"node_modules/react/lib/ReactRef.js","original":{"line":23,"column":4}},{"generated":{"line":24,"column":0},"source":"node_modules/react/lib/ReactRef.js","original":{"line":24,"column":3}},{"generated":{"line":25,"column":0},"source":"node_modules/react/lib/ReactRef.js","original":{"line":25,"column":1}},{"generated":{"line":27,"column":0},"source":"node_modules/react/lib/ReactRef.js","original":{"line":27,"column":0}},{"name":"detachRef","generated":{"line":27,"column":9},"source":"node_modules/react/lib/ReactRef.js","original":{"line":27,"column":9}},{"generated":{"line":27,"column":18},"source":"node_modules/react/lib/ReactRef.js","original":{"line":27,"column":0}},{"name":"ref","generated":{"line":27,"column":19},"source":"node_modules/react/lib/ReactRef.js","original":{"line":27,"column":19}},{"generated":{"line":27,"column":22},"source":"node_modules/react/lib/ReactRef.js","original":{"line":27,"column":0}},{"name":"component","generated":{"line":27,"column":24},"source":"node_modules/react/lib/ReactRef.js","original":{"line":27,"column":24}},{"generated":{"line":27,"column":33},"source":"node_modules/react/lib/ReactRef.js","original":{"line":27,"column":0}},{"name":"owner","generated":{"line":27,"column":35},"source":"node_modules/react/lib/ReactRef.js","original":{"line":27,"column":35}},{"generated":{"line":27,"column":40},"source":"node_modules/react/lib/ReactRef.js","original":{"line":27,"column":0}},{"generated":{"line":27,"column":42},"source":"node_modules/react/lib/ReactRef.js","original":{"line":27,"column":42}},{"generated":{"line":28,"column":0},"source":"node_modules/react/lib/ReactRef.js","original":{"line":28,"column":2}},{"generated":{"line":28,"column":6},"source":"node_modules/react/lib/ReactRef.js","original":{"line":28,"column":6}},{"name":"ref","generated":{"line":28,"column":13},"source":"node_modules/react/lib/ReactRef.js","original":{"line":28,"column":13}},{"generated":{"line":28,"column":16},"source":"node_modules/react/lib/ReactRef.js","original":{"line":28,"column":6}},{"generated":{"line":28,"column":21},"source":"node_modules/react/lib/ReactRef.js","original":{"line":28,"column":21}},{"generated":{"line":28,"column":31},"source":"node_modules/react/lib/ReactRef.js","original":{"line":28,"column":2}},{"generated":{"line":28,"column":33},"source":"node_modules/react/lib/ReactRef.js","original":{"line":28,"column":33}},{"name":"ref","generated":{"line":29,"column":0},"source":"node_modules/react/lib/ReactRef.js","original":{"line":29,"column":4}},{"generated":{"line":29,"column":8},"source":"node_modules/react/lib/ReactRef.js","original":{"line":29,"column":8}},{"generated":{"line":29,"column":12},"source":"node_modules/react/lib/ReactRef.js","original":{"line":29,"column":4}},{"generated":{"line":30,"column":0},"source":"node_modules/react/lib/ReactRef.js","original":{"line":30,"column":3}},{"generated":{"line":30,"column":3},"source":"node_modules/react/lib/ReactRef.js","original":{"line":28,"column":2}},{"generated":{"line":30,"column":9},"source":"node_modules/react/lib/ReactRef.js","original":{"line":30,"column":9}},{"generated":{"line":31,"column":0},"source":"node_modules/react/lib/ReactRef.js","original":{"line":31,"column":4}},{"name":"ReactOwner","generated":{"line":32,"column":0},"source":"node_modules/react/lib/ReactRef.js","original":{"line":32,"column":4}},{"name":"removeComponentAsRefFrom","generated":{"line":32,"column":15},"source":"node_modules/react/lib/ReactRef.js","original":{"line":32,"column":15}},{"generated":{"line":32,"column":39},"source":"node_modules/react/lib/ReactRef.js","original":{"line":32,"column":4}},{"name":"component","generated":{"line":32,"column":40},"source":"node_modules/react/lib/ReactRef.js","original":{"line":32,"column":40}},{"generated":{"line":32,"column":49},"source":"node_modules/react/lib/ReactRef.js","original":{"line":32,"column":4}},{"name":"ref","generated":{"line":32,"column":51},"source":"node_modules/react/lib/ReactRef.js","original":{"line":32,"column":51}},{"generated":{"line":32,"column":54},"source":"node_modules/react/lib/ReactRef.js","original":{"line":32,"column":4}},{"name":"owner","generated":{"line":32,"column":56},"source":"node_modules/react/lib/ReactRef.js","original":{"line":32,"column":56}},{"generated":{"line":32,"column":61},"source":"node_modules/react/lib/ReactRef.js","original":{"line":32,"column":4}},{"generated":{"line":33,"column":0},"source":"node_modules/react/lib/ReactRef.js","original":{"line":33,"column":3}},{"generated":{"line":34,"column":0},"source":"node_modules/react/lib/ReactRef.js","original":{"line":34,"column":1}},{"name":"ReactRef","generated":{"line":36,"column":0},"source":"node_modules/react/lib/ReactRef.js","original":{"line":36,"column":0}},{"name":"attachRefs","generated":{"line":36,"column":9},"source":"node_modules/react/lib/ReactRef.js","original":{"line":36,"column":9}},{"generated":{"line":36,"column":19},"source":"node_modules/react/lib/ReactRef.js","original":{"line":36,"column":0}},{"generated":{"line":36,"column":22},"source":"node_modules/react/lib/ReactRef.js","original":{"line":36,"column":22}},{"name":"instance","generated":{"line":36,"column":32},"source":"node_modules/react/lib/ReactRef.js","original":{"line":36,"column":32}},{"generated":{"line":36,"column":40},"source":"node_modules/react/lib/ReactRef.js","original":{"line":36,"column":22}},{"name":"element","generated":{"line":36,"column":42},"source":"node_modules/react/lib/ReactRef.js","original":{"line":36,"column":42}},{"generated":{"line":36,"column":49},"source":"node_modules/react/lib/ReactRef.js","original":{"line":36,"column":22}},{"generated":{"line":36,"column":51},"source":"node_modules/react/lib/ReactRef.js","original":{"line":36,"column":51}},{"generated":{"line":37,"column":0},"source":"node_modules/react/lib/ReactRef.js","original":{"line":37,"column":2}},{"name":"element","generated":{"line":37,"column":6},"source":"node_modules/react/lib/ReactRef.js","original":{"line":37,"column":6}},{"generated":{"line":37,"column":18},"source":"node_modules/react/lib/ReactRef.js","original":{"line":37,"column":18}},{"generated":{"line":37,"column":22},"source":"node_modules/react/lib/ReactRef.js","original":{"line":37,"column":6}},{"name":"element","generated":{"line":37,"column":26},"source":"node_modules/react/lib/ReactRef.js","original":{"line":37,"column":26}},{"generated":{"line":37,"column":38},"source":"node_modules/react/lib/ReactRef.js","original":{"line":37,"column":38}},{"generated":{"line":37,"column":43},"source":"node_modules/react/lib/ReactRef.js","original":{"line":37,"column":2}},{"generated":{"line":37,"column":45},"source":"node_modules/react/lib/ReactRef.js","original":{"line":37,"column":45}},{"generated":{"line":38,"column":0},"source":"node_modules/react/lib/ReactRef.js","original":{"line":38,"column":4}},{"generated":{"line":39,"column":0},"source":"node_modules/react/lib/ReactRef.js","original":{"line":39,"column":3}},{"generated":{"line":40,"column":0},"source":"node_modules/react/lib/ReactRef.js","original":{"line":40,"column":2}},{"name":"ref","generated":{"line":40,"column":6},"source":"node_modules/react/lib/ReactRef.js","original":{"line":40,"column":6}},{"name":"element","generated":{"line":40,"column":12},"source":"node_modules/react/lib/ReactRef.js","original":{"line":40,"column":12}},{"name":"ref","generated":{"line":40,"column":20},"source":"node_modules/react/lib/ReactRef.js","original":{"line":40,"column":20}},{"generated":{"line":40,"column":23},"source":"node_modules/react/lib/ReactRef.js","original":{"line":40,"column":2}},{"generated":{"line":41,"column":0},"source":"node_modules/react/lib/ReactRef.js","original":{"line":41,"column":2}},{"name":"ref","generated":{"line":41,"column":6},"source":"node_modules/react/lib/ReactRef.js","original":{"line":41,"column":6}},{"generated":{"line":41,"column":13},"source":"node_modules/react/lib/ReactRef.js","original":{"line":41,"column":13}},{"generated":{"line":41,"column":17},"source":"node_modules/react/lib/ReactRef.js","original":{"line":41,"column":2}},{"generated":{"line":41,"column":19},"source":"node_modules/react/lib/ReactRef.js","original":{"line":41,"column":19}},{"name":"attachRef","generated":{"line":42,"column":0},"source":"node_modules/react/lib/ReactRef.js","original":{"line":42,"column":4}},{"name":"ref","generated":{"line":42,"column":14},"source":"node_modules/react/lib/ReactRef.js","original":{"line":42,"column":14}},{"generated":{"line":42,"column":17},"source":"node_modules/react/lib/ReactRef.js","original":{"line":42,"column":4}},{"name":"instance","generated":{"line":42,"column":19},"source":"node_modules/react/lib/ReactRef.js","original":{"line":42,"column":19}},{"generated":{"line":42,"column":27},"source":"node_modules/react/lib/ReactRef.js","original":{"line":42,"column":4}},{"name":"element","generated":{"line":42,"column":29},"source":"node_modules/react/lib/ReactRef.js","original":{"line":42,"column":29}},{"name":"_owner","generated":{"line":42,"column":37},"source":"node_modules/react/lib/ReactRef.js","original":{"line":42,"column":37}},{"generated":{"line":42,"column":43},"source":"node_modules/react/lib/ReactRef.js","original":{"line":42,"column":4}},{"generated":{"line":43,"column":0},"source":"node_modules/react/lib/ReactRef.js","original":{"line":43,"column":3}},{"generated":{"line":44,"column":0},"source":"node_modules/react/lib/ReactRef.js","original":{"line":44,"column":1}},{"generated":{"line":44,"column":1},"source":"node_modules/react/lib/ReactRef.js","original":{"line":36,"column":0}},{"name":"ReactRef","generated":{"line":46,"column":0},"source":"node_modules/react/lib/ReactRef.js","original":{"line":46,"column":0}},{"name":"shouldUpdateRefs","generated":{"line":46,"column":9},"source":"node_modules/react/lib/ReactRef.js","original":{"line":46,"column":9}},{"generated":{"line":46,"column":25},"source":"node_modules/react/lib/ReactRef.js","original":{"line":46,"column":0}},{"generated":{"line":46,"column":28},"source":"node_modules/react/lib/ReactRef.js","original":{"line":46,"column":28}},{"name":"prevElement","generated":{"line":46,"column":38},"source":"node_modules/react/lib/ReactRef.js","original":{"line":46,"column":38}},{"generated":{"line":46,"column":49},"source":"node_modules/react/lib/ReactRef.js","original":{"line":46,"column":28}},{"name":"nextElement","generated":{"line":46,"column":51},"source":"node_modules/react/lib/ReactRef.js","original":{"line":46,"column":51}},{"generated":{"line":46,"column":62},"source":"node_modules/react/lib/ReactRef.js","original":{"line":46,"column":28}},{"generated":{"line":46,"column":64},"source":"node_modules/react/lib/ReactRef.js","original":{"line":46,"column":64}},{"generated":{"line":47,"column":0},"source":"node_modules/react/lib/ReactRef.js","original":{"line":47,"column":2}},{"generated":{"line":48,"column":0},"source":"node_modules/react/lib/ReactRef.js","original":{"line":48,"column":2}},{"generated":{"line":49,"column":0},"source":"node_modules/react/lib/ReactRef.js","original":{"line":49,"column":2}},{"generated":{"line":50,"column":0},"source":"node_modules/react/lib/ReactRef.js","original":{"line":50,"column":2}},{"generated":{"line":51,"column":0},"source":"node_modules/react/lib/ReactRef.js","original":{"line":51,"column":2}},{"generated":{"line":53,"column":0},"source":"node_modules/react/lib/ReactRef.js","original":{"line":53,"column":2}},{"generated":{"line":54,"column":0},"source":"node_modules/react/lib/ReactRef.js","original":{"line":54,"column":2}},{"generated":{"line":55,"column":0},"source":"node_modules/react/lib/ReactRef.js","original":{"line":55,"column":2}},{"generated":{"line":56,"column":0},"source":"node_modules/react/lib/ReactRef.js","original":{"line":56,"column":2}},{"generated":{"line":57,"column":0},"source":"node_modules/react/lib/ReactRef.js","original":{"line":57,"column":2}},{"generated":{"line":59,"column":0},"source":"node_modules/react/lib/ReactRef.js","original":{"line":59,"column":2}},{"name":"prevEmpty","generated":{"line":59,"column":6},"source":"node_modules/react/lib/ReactRef.js","original":{"line":59,"column":6}},{"name":"prevElement","generated":{"line":59,"column":18},"source":"node_modules/react/lib/ReactRef.js","original":{"line":59,"column":18}},{"generated":{"line":59,"column":34},"source":"node_modules/react/lib/ReactRef.js","original":{"line":59,"column":34}},{"generated":{"line":59,"column":38},"source":"node_modules/react/lib/ReactRef.js","original":{"line":59,"column":18}},{"name":"prevElement","generated":{"line":59,"column":42},"source":"node_modules/react/lib/ReactRef.js","original":{"line":59,"column":42}},{"generated":{"line":59,"column":58},"source":"node_modules/react/lib/ReactRef.js","original":{"line":59,"column":58}},{"generated":{"line":59,"column":63},"source":"node_modules/react/lib/ReactRef.js","original":{"line":59,"column":2}},{"generated":{"line":60,"column":0},"source":"node_modules/react/lib/ReactRef.js","original":{"line":60,"column":2}},{"name":"nextEmpty","generated":{"line":60,"column":6},"source":"node_modules/react/lib/ReactRef.js","original":{"line":60,"column":6}},{"name":"nextElement","generated":{"line":60,"column":18},"source":"node_modules/react/lib/ReactRef.js","original":{"line":60,"column":18}},{"generated":{"line":60,"column":34},"source":"node_modules/react/lib/ReactRef.js","original":{"line":60,"column":34}},{"generated":{"line":60,"column":38},"source":"node_modules/react/lib/ReactRef.js","original":{"line":60,"column":18}},{"name":"nextElement","generated":{"line":60,"column":42},"source":"node_modules/react/lib/ReactRef.js","original":{"line":60,"column":42}},{"generated":{"line":60,"column":58},"source":"node_modules/react/lib/ReactRef.js","original":{"line":60,"column":58}},{"generated":{"line":60,"column":63},"source":"node_modules/react/lib/ReactRef.js","original":{"line":60,"column":2}},{"generated":{"line":62,"column":0},"source":"node_modules/react/lib/ReactRef.js","original":{"line":62,"column":2}},{"generated":{"line":63,"column":0},"source":"node_modules/react/lib/ReactRef.js","original":{"line":63,"column":4}},{"name":"prevEmpty","generated":{"line":64,"column":0},"source":"node_modules/react/lib/ReactRef.js","original":{"line":64,"column":4}},{"name":"nextEmpty","generated":{"line":64,"column":17},"source":"node_modules/react/lib/ReactRef.js","original":{"line":64,"column":17}},{"generated":{"line":64,"column":26},"source":"node_modules/react/lib/ReactRef.js","original":{"line":64,"column":4}},{"name":"nextElement","generated":{"line":64,"column":30},"source":"node_modules/react/lib/ReactRef.js","original":{"line":64,"column":30}},{"name":"ref","generated":{"line":64,"column":42},"source":"node_modules/react/lib/ReactRef.js","original":{"line":64,"column":42}},{"generated":{"line":64,"column":45},"source":"node_modules/react/lib/ReactRef.js","original":{"line":64,"column":30}},{"name":"prevElement","generated":{"line":64,"column":50},"source":"node_modules/react/lib/ReactRef.js","original":{"line":64,"column":50}},{"name":"ref","generated":{"line":64,"column":62},"source":"node_modules/react/lib/ReactRef.js","original":{"line":64,"column":62}},{"generated":{"line":64,"column":65},"source":"node_modules/react/lib/ReactRef.js","original":{"line":64,"column":4}},{"generated":{"line":65,"column":0},"source":"node_modules/react/lib/ReactRef.js","original":{"line":65,"column":4}},{"generated":{"line":66,"column":0},"source":"node_modules/react/lib/ReactRef.js","original":{"line":66,"column":4}},{"name":"nextElement","generated":{"line":66,"column":11},"source":"node_modules/react/lib/ReactRef.js","original":{"line":66,"column":11}},{"name":"ref","generated":{"line":66,"column":23},"source":"node_modules/react/lib/ReactRef.js","original":{"line":66,"column":23}},{"generated":{"line":66,"column":26},"source":"node_modules/react/lib/ReactRef.js","original":{"line":66,"column":4}},{"generated":{"line":66,"column":31},"source":"node_modules/react/lib/ReactRef.js","original":{"line":66,"column":31}},{"generated":{"line":66,"column":39},"source":"node_modules/react/lib/ReactRef.js","original":{"line":66,"column":4}},{"name":"nextElement","generated":{"line":66,"column":43},"source":"node_modules/react/lib/ReactRef.js","original":{"line":66,"column":43}},{"name":"_owner","generated":{"line":66,"column":55},"source":"node_modules/react/lib/ReactRef.js","original":{"line":66,"column":55}},{"generated":{"line":66,"column":61},"source":"node_modules/react/lib/ReactRef.js","original":{"line":66,"column":43}},{"name":"prevElement","generated":{"line":66,"column":66},"source":"node_modules/react/lib/ReactRef.js","original":{"line":66,"column":66}},{"name":"_owner","generated":{"line":66,"column":78},"source":"node_modules/react/lib/ReactRef.js","original":{"line":66,"column":78}},{"generated":{"line":67,"column":0},"source":"node_modules/react/lib/ReactRef.js","original":{"line":62,"column":2}},{"generated":{"line":68,"column":0},"source":"node_modules/react/lib/ReactRef.js","original":{"line":68,"column":1}},{"generated":{"line":68,"column":1},"source":"node_modules/react/lib/ReactRef.js","original":{"line":46,"column":0}},{"name":"ReactRef","generated":{"line":70,"column":0},"source":"node_modules/react/lib/ReactRef.js","original":{"line":70,"column":0}},{"name":"detachRefs","generated":{"line":70,"column":9},"source":"node_modules/react/lib/ReactRef.js","original":{"line":70,"column":9}},{"generated":{"line":70,"column":19},"source":"node_modules/react/lib/ReactRef.js","original":{"line":70,"column":0}},{"generated":{"line":70,"column":22},"source":"node_modules/react/lib/ReactRef.js","original":{"line":70,"column":22}},{"name":"instance","generated":{"line":70,"column":32},"source":"node_modules/react/lib/ReactRef.js","original":{"line":70,"column":32}},{"generated":{"line":70,"column":40},"source":"node_modules/react/lib/ReactRef.js","original":{"line":70,"column":22}},{"name":"element","generated":{"line":70,"column":42},"source":"node_modules/react/lib/ReactRef.js","original":{"line":70,"column":42}},{"generated":{"line":70,"column":49},"source":"node_modules/react/lib/ReactRef.js","original":{"line":70,"column":22}},{"generated":{"line":70,"column":51},"source":"node_modules/react/lib/ReactRef.js","original":{"line":70,"column":51}},{"generated":{"line":71,"column":0},"source":"node_modules/react/lib/ReactRef.js","original":{"line":71,"column":2}},{"name":"element","generated":{"line":71,"column":6},"source":"node_modules/react/lib/ReactRef.js","original":{"line":71,"column":6}},{"generated":{"line":71,"column":18},"source":"node_modules/react/lib/ReactRef.js","original":{"line":71,"column":18}},{"generated":{"line":71,"column":22},"source":"node_modules/react/lib/ReactRef.js","original":{"line":71,"column":6}},{"name":"element","generated":{"line":71,"column":26},"source":"node_modules/react/lib/ReactRef.js","original":{"line":71,"column":26}},{"generated":{"line":71,"column":38},"source":"node_modules/react/lib/ReactRef.js","original":{"line":71,"column":38}},{"generated":{"line":71,"column":43},"source":"node_modules/react/lib/ReactRef.js","original":{"line":71,"column":2}},{"generated":{"line":71,"column":45},"source":"node_modules/react/lib/ReactRef.js","original":{"line":71,"column":45}},{"generated":{"line":72,"column":0},"source":"node_modules/react/lib/ReactRef.js","original":{"line":72,"column":4}},{"generated":{"line":73,"column":0},"source":"node_modules/react/lib/ReactRef.js","original":{"line":73,"column":3}},{"generated":{"line":74,"column":0},"source":"node_modules/react/lib/ReactRef.js","original":{"line":74,"column":2}},{"name":"ref","generated":{"line":74,"column":6},"source":"node_modules/react/lib/ReactRef.js","original":{"line":74,"column":6}},{"name":"element","generated":{"line":74,"column":12},"source":"node_modules/react/lib/ReactRef.js","original":{"line":74,"column":12}},{"name":"ref","generated":{"line":74,"column":20},"source":"node_modules/react/lib/ReactRef.js","original":{"line":74,"column":20}},{"generated":{"line":74,"column":23},"source":"node_modules/react/lib/ReactRef.js","original":{"line":74,"column":2}},{"generated":{"line":75,"column":0},"source":"node_modules/react/lib/ReactRef.js","original":{"line":75,"column":2}},{"name":"ref","generated":{"line":75,"column":6},"source":"node_modules/react/lib/ReactRef.js","original":{"line":75,"column":6}},{"generated":{"line":75,"column":13},"source":"node_modules/react/lib/ReactRef.js","original":{"line":75,"column":13}},{"generated":{"line":75,"column":17},"source":"node_modules/react/lib/ReactRef.js","original":{"line":75,"column":2}},{"generated":{"line":75,"column":19},"source":"node_modules/react/lib/ReactRef.js","original":{"line":75,"column":19}},{"name":"detachRef","generated":{"line":76,"column":0},"source":"node_modules/react/lib/ReactRef.js","original":{"line":76,"column":4}},{"name":"ref","generated":{"line":76,"column":14},"source":"node_modules/react/lib/ReactRef.js","original":{"line":76,"column":14}},{"generated":{"line":76,"column":17},"source":"node_modules/react/lib/ReactRef.js","original":{"line":76,"column":4}},{"name":"instance","generated":{"line":76,"column":19},"source":"node_modules/react/lib/ReactRef.js","original":{"line":76,"column":19}},{"generated":{"line":76,"column":27},"source":"node_modules/react/lib/ReactRef.js","original":{"line":76,"column":4}},{"name":"element","generated":{"line":76,"column":29},"source":"node_modules/react/lib/ReactRef.js","original":{"line":76,"column":29}},{"name":"_owner","generated":{"line":76,"column":37},"source":"node_modules/react/lib/ReactRef.js","original":{"line":76,"column":37}},{"generated":{"line":76,"column":43},"source":"node_modules/react/lib/ReactRef.js","original":{"line":76,"column":4}},{"generated":{"line":77,"column":0},"source":"node_modules/react/lib/ReactRef.js","original":{"line":77,"column":3}},{"generated":{"line":78,"column":0},"source":"node_modules/react/lib/ReactRef.js","original":{"line":78,"column":1}},{"generated":{"line":78,"column":1},"source":"node_modules/react/lib/ReactRef.js","original":{"line":70,"column":0}},{"name":"module","generated":{"line":80,"column":0},"source":"node_modules/react/lib/ReactRef.js","original":{"line":80,"column":0}},{"name":"exports","generated":{"line":80,"column":7},"source":"node_modules/react/lib/ReactRef.js","original":{"line":80,"column":7}},{"generated":{"line":80,"column":14},"source":"node_modules/react/lib/ReactRef.js","original":{"line":80,"column":0}},{"name":"ReactRef","generated":{"line":80,"column":17},"source":"node_modules/react/lib/ReactRef.js","original":{"line":80,"column":17}},{"generated":{"line":80,"column":25},"source":"node_modules/react/lib/ReactRef.js","original":{"line":80,"column":0}}],"sources":{"node_modules/react/lib/ReactRef.js":"/**\n * Copyright 2013-present, Facebook, Inc.\n * All rights reserved.\n *\n * This source code is licensed under the BSD-style license found in the\n * LICENSE file in the root directory of this source tree. An additional grant\n * of patent rights can be found in the PATENTS file in the same directory.\n *\n * @providesModule ReactRef\n */\n\n'use strict';\n\nvar ReactOwner = require('./ReactOwner');\n\nvar ReactRef = {};\n\nfunction attachRef(ref, component, owner) {\n  if (typeof ref === 'function') {\n    ref(component.getPublicInstance());\n  } else {\n    // Legacy ref\n    ReactOwner.addComponentAsRefTo(component, ref, owner);\n  }\n}\n\nfunction detachRef(ref, component, owner) {\n  if (typeof ref === 'function') {\n    ref(null);\n  } else {\n    // Legacy ref\n    ReactOwner.removeComponentAsRefFrom(component, ref, owner);\n  }\n}\n\nReactRef.attachRefs = function (instance, element) {\n  if (element === null || element === false) {\n    return;\n  }\n  var ref = element.ref;\n  if (ref != null) {\n    attachRef(ref, instance, element._owner);\n  }\n};\n\nReactRef.shouldUpdateRefs = function (prevElement, nextElement) {\n  // If either the owner or a `ref` has changed, make sure the newest owner\n  // has stored a reference to `this`, and the previous owner (if different)\n  // has forgotten the reference to `this`. We use the element instead\n  // of the public this.props because the post processing cannot determine\n  // a ref. The ref conceptually lives on the element.\n\n  // TODO: Should this even be possible? The owner cannot change because\n  // it's forbidden by shouldUpdateReactComponent. The ref can change\n  // if you swap the keys of but not the refs. Reconsider where this check\n  // is made. It probably belongs where the key checking and\n  // instantiateReactComponent is done.\n\n  var prevEmpty = prevElement === null || prevElement === false;\n  var nextEmpty = nextElement === null || nextElement === false;\n\n  return (\n    // This has a few false positives w/r/t empty components.\n    prevEmpty || nextEmpty || nextElement.ref !== prevElement.ref ||\n    // If owner changes but we have an unchanged function ref, don't update refs\n    typeof nextElement.ref === 'string' && nextElement._owner !== prevElement._owner\n  );\n};\n\nReactRef.detachRefs = function (instance, element) {\n  if (element === null || element === false) {\n    return;\n  }\n  var ref = element.ref;\n  if (ref != null) {\n    detachRef(ref, instance, element._owner);\n  }\n};\n\nmodule.exports = ReactRef;"},"lineCount":null}},"hash":"aecbfa68a1dccd3d3677060be3a099f9","cacheData":{"env":{}}}