{"id":"PtNC","dependencies":[{"name":"/Users/Mikey/Programming/open-source/react-scaffold/node_modules/redux/package.json","includedInParent":true,"mtime":1534193415135},{"name":"/Users/Mikey/Programming/open-source/react-scaffold/package.json","includedInParent":true,"mtime":1534200257736},{"name":"/Users/Mikey/Programming/open-source/react-scaffold/.babelrc","includedInParent":true,"mtime":1534195938169},{"name":"./createStore","loc":{"line":1,"column":24},"parent":"/Users/Mikey/Programming/open-source/react-scaffold/node_modules/redux/es/index.js","resolved":"/Users/Mikey/Programming/open-source/react-scaffold/node_modules/redux/es/createStore.js"},{"name":"./combineReducers","loc":{"line":2,"column":28},"parent":"/Users/Mikey/Programming/open-source/react-scaffold/node_modules/redux/es/index.js","resolved":"/Users/Mikey/Programming/open-source/react-scaffold/node_modules/redux/es/combineReducers.js"},{"name":"./bindActionCreators","loc":{"line":3,"column":31},"parent":"/Users/Mikey/Programming/open-source/react-scaffold/node_modules/redux/es/index.js","resolved":"/Users/Mikey/Programming/open-source/react-scaffold/node_modules/redux/es/bindActionCreators.js"},{"name":"./applyMiddleware","loc":{"line":4,"column":28},"parent":"/Users/Mikey/Programming/open-source/react-scaffold/node_modules/redux/es/index.js","resolved":"/Users/Mikey/Programming/open-source/react-scaffold/node_modules/redux/es/applyMiddleware.js"},{"name":"./compose","loc":{"line":5,"column":20},"parent":"/Users/Mikey/Programming/open-source/react-scaffold/node_modules/redux/es/index.js","resolved":"/Users/Mikey/Programming/open-source/react-scaffold/node_modules/redux/es/compose.js"},{"name":"./utils/warning","loc":{"line":6,"column":20},"parent":"/Users/Mikey/Programming/open-source/react-scaffold/node_modules/redux/es/index.js","resolved":"/Users/Mikey/Programming/open-source/react-scaffold/node_modules/redux/es/utils/warning.js"}],"generated":{"js":"\"use strict\";Object.defineProperty(exports,\"__esModule\",{value:!0}),exports.compose=exports.applyMiddleware=exports.bindActionCreators=exports.combineReducers=exports.createStore=void 0;var e=require(\"./createStore\"),r=l(e),t=require(\"./combineReducers\"),o=l(t),i=require(\"./bindActionCreators\"),s=l(i),u=require(\"./applyMiddleware\"),d=l(u),a=require(\"./compose\"),p=l(a),c=require(\"./utils/warning\"),n=l(c);function l(e){return e&&e.__esModule?e:{default:e}}function x(){}exports.createStore=r.default,exports.combineReducers=o.default,exports.bindActionCreators=s.default,exports.applyMiddleware=d.default,exports.compose=p.default;","map":{"mappings":[{"source":"node_modules/redux/es/index.js","name":"compose","original":{"line":18,"column":76},"generated":{"line":1,"column":0}},{"source":"node_modules/redux/es/index.js","name":"compose","original":{"line":18,"column":76},"generated":{"line":1,"column":13}},{"source":"node_modules/redux/es/index.js","name":"compose","original":{"line":18,"column":76},"generated":{"line":1,"column":20}},{"source":"node_modules/redux/es/index.js","name":"compose","original":{"line":18,"column":76},"generated":{"line":1,"column":35}},{"source":"node_modules/redux/es/index.js","name":"compose","original":{"line":18,"column":76},"generated":{"line":1,"column":43}},{"source":"node_modules/redux/es/index.js","name":"compose","original":{"line":18,"column":76},"generated":{"line":1,"column":56}},{"source":"node_modules/redux/es/index.js","name":"compose","original":{"line":18,"column":76},"generated":{"line":1,"column":57}},{"source":"node_modules/redux/es/index.js","name":"compose","original":{"line":18,"column":76},"generated":{"line":1,"column":64}},{"source":"node_modules/redux/es/index.js","name":"compose","original":{"line":18,"column":76},"generated":{"line":1,"column":68}},{"source":"node_modules/redux/es/index.js","name":"compose","original":{"line":18,"column":76},"generated":{"line":1,"column":76}},{"source":"node_modules/redux/es/index.js","name":"compose","original":{"line":18,"column":76},"generated":{"line":1,"column":84}},{"source":"node_modules/redux/es/index.js","name":"compose","original":{"line":18,"column":76},"generated":{"line":1,"column":92}},{"source":"node_modules/redux/es/index.js","name":"compose","original":{"line":18,"column":76},"generated":{"line":1,"column":108}},{"source":"node_modules/redux/es/index.js","name":"compose","original":{"line":18,"column":76},"generated":{"line":1,"column":116}},{"source":"node_modules/redux/es/index.js","name":"compose","original":{"line":18,"column":76},"generated":{"line":1,"column":135}},{"source":"node_modules/redux/es/index.js","name":"compose","original":{"line":18,"column":76},"generated":{"line":1,"column":143}},{"source":"node_modules/redux/es/index.js","name":"compose","original":{"line":18,"column":76},"generated":{"line":1,"column":159}},{"source":"node_modules/redux/es/index.js","name":"compose","original":{"line":18,"column":76},"generated":{"line":1,"column":167}},{"source":"node_modules/redux/es/index.js","name":"compose","original":{"line":18,"column":76},"generated":{"line":1,"column":184}},{"source":"node_modules/redux/es/index.js","original":{"line":1,"column":0},"generated":{"line":1,"column":186}},{"source":"node_modules/redux/es/index.js","original":{"line":1,"column":0},"generated":{"line":1,"column":190}},{"source":"node_modules/redux/es/index.js","original":{"line":1,"column":0},"generated":{"line":1,"column":192}},{"source":"node_modules/redux/es/index.js","original":{"line":1,"column":0},"generated":{"line":1,"column":200}},{"source":"node_modules/redux/es/index.js","name":"compose","original":{"line":18,"column":76},"generated":{"line":1,"column":217}},{"source":"node_modules/redux/es/index.js","name":"compose","original":{"line":18,"column":76},"generated":{"line":1,"column":219}},{"source":"node_modules/redux/es/index.js","name":"compose","original":{"line":18,"column":76},"generated":{"line":1,"column":221}},{"source":"node_modules/redux/es/index.js","original":{"line":2,"column":0},"generated":{"line":1,"column":224}},{"source":"node_modules/redux/es/index.js","original":{"line":2,"column":0},"generated":{"line":1,"column":226}},{"source":"node_modules/redux/es/index.js","original":{"line":2,"column":0},"generated":{"line":1,"column":234}},{"source":"node_modules/redux/es/index.js","name":"compose","original":{"line":18,"column":76},"generated":{"line":1,"column":255}},{"source":"node_modules/redux/es/index.js","name":"compose","original":{"line":18,"column":76},"generated":{"line":1,"column":257}},{"source":"node_modules/redux/es/index.js","name":"compose","original":{"line":18,"column":76},"generated":{"line":1,"column":259}},{"source":"node_modules/redux/es/index.js","original":{"line":3,"column":0},"generated":{"line":1,"column":262}},{"source":"node_modules/redux/es/index.js","original":{"line":3,"column":0},"generated":{"line":1,"column":264}},{"source":"node_modules/redux/es/index.js","original":{"line":3,"column":0},"generated":{"line":1,"column":272}},{"source":"node_modules/redux/es/index.js","name":"compose","original":{"line":18,"column":76},"generated":{"line":1,"column":296}},{"source":"node_modules/redux/es/index.js","name":"compose","original":{"line":18,"column":76},"generated":{"line":1,"column":298}},{"source":"node_modules/redux/es/index.js","name":"compose","original":{"line":18,"column":76},"generated":{"line":1,"column":300}},{"source":"node_modules/redux/es/index.js","original":{"line":4,"column":0},"generated":{"line":1,"column":303}},{"source":"node_modules/redux/es/index.js","original":{"line":4,"column":0},"generated":{"line":1,"column":305}},{"source":"node_modules/redux/es/index.js","original":{"line":4,"column":0},"generated":{"line":1,"column":313}},{"source":"node_modules/redux/es/index.js","name":"compose","original":{"line":18,"column":76},"generated":{"line":1,"column":334}},{"source":"node_modules/redux/es/index.js","name":"compose","original":{"line":18,"column":76},"generated":{"line":1,"column":336}},{"source":"node_modules/redux/es/index.js","name":"compose","original":{"line":18,"column":76},"generated":{"line":1,"column":338}},{"source":"node_modules/redux/es/index.js","original":{"line":5,"column":0},"generated":{"line":1,"column":341}},{"source":"node_modules/redux/es/index.js","original":{"line":5,"column":0},"generated":{"line":1,"column":343}},{"source":"node_modules/redux/es/index.js","original":{"line":5,"column":0},"generated":{"line":1,"column":351}},{"source":"node_modules/redux/es/index.js","name":"compose","original":{"line":18,"column":76},"generated":{"line":1,"column":364}},{"source":"node_modules/redux/es/index.js","name":"compose","original":{"line":18,"column":76},"generated":{"line":1,"column":366}},{"source":"node_modules/redux/es/index.js","name":"compose","original":{"line":18,"column":76},"generated":{"line":1,"column":368}},{"source":"node_modules/redux/es/index.js","original":{"line":6,"column":0},"generated":{"line":1,"column":371}},{"source":"node_modules/redux/es/index.js","original":{"line":6,"column":0},"generated":{"line":1,"column":373}},{"source":"node_modules/redux/es/index.js","original":{"line":6,"column":0},"generated":{"line":1,"column":381}},{"source":"node_modules/redux/es/index.js","name":"compose","original":{"line":18,"column":76},"generated":{"line":1,"column":400}},{"source":"node_modules/redux/es/index.js","name":"compose","original":{"line":18,"column":76},"generated":{"line":1,"column":402}},{"source":"node_modules/redux/es/index.js","name":"compose","original":{"line":18,"column":76},"generated":{"line":1,"column":404}},{"source":"node_modules/redux/es/index.js","name":"compose","original":{"line":18,"column":76},"generated":{"line":1,"column":407}},{"source":"node_modules/redux/es/index.js","name":"compose","original":{"line":18,"column":76},"generated":{"line":1,"column":416}},{"source":"node_modules/redux/es/index.js","name":"compose","original":{"line":18,"column":76},"generated":{"line":1,"column":418}},{"source":"node_modules/redux/es/index.js","name":"compose","original":{"line":18,"column":76},"generated":{"line":1,"column":421}},{"source":"node_modules/redux/es/index.js","name":"compose","original":{"line":18,"column":76},"generated":{"line":1,"column":428}},{"source":"node_modules/redux/es/index.js","name":"compose","original":{"line":18,"column":76},"generated":{"line":1,"column":431}},{"source":"node_modules/redux/es/index.js","name":"compose","original":{"line":18,"column":76},"generated":{"line":1,"column":433}},{"source":"node_modules/redux/es/index.js","name":"compose","original":{"line":18,"column":76},"generated":{"line":1,"column":444}},{"source":"node_modules/redux/es/index.js","name":"compose","original":{"line":18,"column":76},"generated":{"line":1,"column":446}},{"source":"node_modules/redux/es/index.js","name":"compose","original":{"line":18,"column":76},"generated":{"line":1,"column":447}},{"source":"node_modules/redux/es/index.js","name":"compose","original":{"line":18,"column":76},"generated":{"line":1,"column":455}},{"source":"node_modules/redux/es/index.js","original":{"line":12,"column":0},"generated":{"line":1,"column":458}},{"source":"node_modules/redux/es/index.js","name":"isCrushed","original":{"line":12,"column":9},"generated":{"line":1,"column":467}},{"source":"node_modules/redux/es/index.js","name":"createStore","original":{"line":18,"column":9},"generated":{"line":1,"column":472}},{"source":"node_modules/redux/es/index.js","name":"createStore","original":{"line":18,"column":9},"generated":{"line":1,"column":480}},{"source":"node_modules/redux/es/index.js","name":"createStore","original":{"line":18,"column":9},"generated":{"line":1,"column":492}},{"source":"node_modules/redux/es/index.js","name":"createStore","original":{"line":18,"column":9},"generated":{"line":1,"column":494}},{"source":"node_modules/redux/es/index.js","name":"combineReducers","original":{"line":18,"column":22},"generated":{"line":1,"column":502}},{"source":"node_modules/redux/es/index.js","name":"combineReducers","original":{"line":18,"column":22},"generated":{"line":1,"column":510}},{"source":"node_modules/redux/es/index.js","name":"combineReducers","original":{"line":18,"column":22},"generated":{"line":1,"column":526}},{"source":"node_modules/redux/es/index.js","name":"combineReducers","original":{"line":18,"column":22},"generated":{"line":1,"column":528}},{"source":"node_modules/redux/es/index.js","name":"bindActionCreators","original":{"line":18,"column":39},"generated":{"line":1,"column":536}},{"source":"node_modules/redux/es/index.js","name":"bindActionCreators","original":{"line":18,"column":39},"generated":{"line":1,"column":544}},{"source":"node_modules/redux/es/index.js","name":"bindActionCreators","original":{"line":18,"column":39},"generated":{"line":1,"column":563}},{"source":"node_modules/redux/es/index.js","name":"bindActionCreators","original":{"line":18,"column":39},"generated":{"line":1,"column":565}},{"source":"node_modules/redux/es/index.js","name":"applyMiddleware","original":{"line":18,"column":59},"generated":{"line":1,"column":573}},{"source":"node_modules/redux/es/index.js","name":"applyMiddleware","original":{"line":18,"column":59},"generated":{"line":1,"column":581}},{"source":"node_modules/redux/es/index.js","name":"applyMiddleware","original":{"line":18,"column":59},"generated":{"line":1,"column":597}},{"source":"node_modules/redux/es/index.js","name":"applyMiddleware","original":{"line":18,"column":59},"generated":{"line":1,"column":599}},{"source":"node_modules/redux/es/index.js","name":"compose","original":{"line":18,"column":76},"generated":{"line":1,"column":607}},{"source":"node_modules/redux/es/index.js","name":"compose","original":{"line":18,"column":76},"generated":{"line":1,"column":615}},{"source":"node_modules/redux/es/index.js","name":"compose","original":{"line":18,"column":76},"generated":{"line":1,"column":623}},{"source":"node_modules/redux/es/index.js","name":"compose","original":{"line":18,"column":76},"generated":{"line":1,"column":625}}],"sources":{"node_modules/redux/es/index.js":"import createStore from './createStore';\nimport combineReducers from './combineReducers';\nimport bindActionCreators from './bindActionCreators';\nimport applyMiddleware from './applyMiddleware';\nimport compose from './compose';\nimport warning from './utils/warning';\n\n/*\n* This is a dummy function to check if the function name has been altered by minification.\n* If the function has been minified and NODE_ENV !== 'production', warn the user.\n*/\nfunction isCrushed() {}\n\nif (process.env.NODE_ENV !== 'production' && typeof isCrushed.name === 'string' && isCrushed.name !== 'isCrushed') {\n  warning('You are currently using minified code outside of NODE_ENV === \\'production\\'. ' + 'This means that you are running a slower development build of Redux. ' + 'You can use loose-envify (https://github.com/zertosh/loose-envify) for browserify ' + 'or DefinePlugin for webpack (http://stackoverflow.com/questions/30030031) ' + 'to ensure you have the correct code for your production build.');\n}\n\nexport { createStore, combineReducers, bindActionCreators, applyMiddleware, compose };"},"lineCount":null}},"hash":"6d4a85796ab69ee7289fc2445c7d6191","cacheData":{"env":{"NODE_ENV":"production"}}}