{"id":"ydxh","dependencies":[{"name":"/Users/Mikey/Programming/open-source/react-scaffold/node_modules/lodash/package.json","includedInParent":true,"mtime":1534193414661},{"name":"/Users/Mikey/Programming/open-source/react-scaffold/package.json","includedInParent":true,"mtime":1534197905411},{"name":"/Users/Mikey/Programming/open-source/react-scaffold/.babelrc","includedInParent":true,"mtime":1534195938169},{"name":"./_root","loc":{"line":1,"column":19},"parent":"/Users/Mikey/Programming/open-source/react-scaffold/node_modules/lodash/_Symbol.js","resolved":"/Users/Mikey/Programming/open-source/react-scaffold/node_modules/lodash/_root.js"}],"generated":{"js":"var o=require(\"./_root\"),r=o.Symbol;module.exports=r;","map":{"mappings":[{"source":"node_modules/lodash/_Symbol.js","original":{"line":1,"column":0},"generated":{"line":1,"column":0}},{"source":"node_modules/lodash/_Symbol.js","original":{"line":1,"column":0},"generated":{"line":1,"column":4}},{"source":"node_modules/lodash/_Symbol.js","original":{"line":1,"column":0},"generated":{"line":1,"column":6}},{"source":"node_modules/lodash/_Symbol.js","original":{"line":1,"column":0},"generated":{"line":1,"column":14}},{"source":"node_modules/lodash/_Symbol.js","original":{"line":4,"column":0},"generated":{"line":1,"column":25}},{"source":"node_modules/lodash/_Symbol.js","original":{"line":4,"column":0},"generated":{"line":1,"column":27}},{"source":"node_modules/lodash/_Symbol.js","original":{"line":4,"column":0},"generated":{"line":1,"column":29}},{"source":"node_modules/lodash/_Symbol.js","original":{"line":6,"column":0},"generated":{"line":1,"column":36}},{"source":"node_modules/lodash/_Symbol.js","original":{"line":6,"column":0},"generated":{"line":1,"column":43}},{"source":"node_modules/lodash/_Symbol.js","original":{"line":6,"column":0},"generated":{"line":1,"column":51}}],"sources":{"node_modules/lodash/_Symbol.js":"var root = require('./_root');\n\n/** Built-in value references. */\nvar Symbol = root.Symbol;\n\nmodule.exports = Symbol;\n"},"lineCount":null}},"hash":"f2830feed1cbd551bbfaa55ff40e5d11","cacheData":{"env":{}}}